{
    "RootType": "saveMetadataContainer",
    "Data": {
        "metadata": {
            "gameDefinition": "",
            "activeQuests": "6B577A51814903CA",
            "trackedQuestEntry": "quests/main_quest/prologue/q005_heist/the_plan/talk_jackie",
            "trackedQuest": "LocKey#9470",
            "mainQuest": "LocKey#9470",
            "debugString": "",
            "locationName": "LocKey#44389",
            "playerPosition": {
                "X": -1463.639404296875,
                "Y": 1047.69677734375,
                "Z": 22.722373962402345
            },
            "playTime": 18855.2056498,
            "playthroughTime": 20406.7904504,
            "nextSavableEntityID": 9002867,
            "nextNonSavableEntityID": 10029122,
            "lifePath": "Nomad",
            "bodyGender": "Female",
            "brainGender": "Female",
            "level": 6.0,
            "streetCred": 4.0,
            "gunslinger": 3.0,
            "assault": 3.0,
            "demolition": 1.0,
            "athletics": 1.0,
            "brawling": 1.0,
            "coldBlood": 1.0,
            "stealth": 1.0,
            "engineering": 1.0,
            "crafting": 1.0,
            "hacking": 1.0,
            "combatHacking": 1.0,
            "strength": 7.0,
            "intelligence": 3.0,
            "reflexes": 7.0,
            "technicalAbility": 3.0,
            "cool": 7.0,
            "initialBuildID": "3.0.3214677  P4CL: 4155897  Stream: //R6.Root/R6.Patch0Hotfix2 ",
            "finishedQuests": "q004 q000 q001 q003 ma_wat_kab_12 ",
            "playthroughID": "5fd612b09766dd3b",
            "pointOfNoReturnId": "",
            "visitID": "591ee216-70bb-4d54-ba73-56dc30e18cc2",
            "buildSKU": "",
            "buildPatch": "1.04",
            "difficulty": "Story",
            "saveVersion": 193,
            "gameVersion": 8,
            "timestampString": "23:36:16, 14.12.2020",
            "name": "QuickSave-0",
            "userName": "",
            "buildID": "3.0.3217599  P4CL: 4158334  Stream: //R6.Root/R6.Patch0Hotfix2 ",
            "platform": "pc",
            "censorFlags": "",
            "buildConfiguration": "final",
            "fileSize": 1796211,
            "isForced": false,
            "isCheckpoint": false,
            "initialLoadingScreenID": 186738114966,
            "isStoryMode": false,
            "isPointOfNoReturn": false,
            "isEndGameSave": false
        }
    }
}